pygination/__init__.py
pygination/errors.py
pygination/py.typed
pygination/pygination.py
pygination/models/__init__.py
pygination/models/page_model.py
pygination-0.0.13.dist-info/METADATA
pygination-0.0.13.dist-info/WHEEL
pygination-0.0.13.dist-info/licenses/LICENSE.txt
pygination-0.0.13.dist-info/RECORD
