Metadata-Version: 2.4
Name: pygination
Version: 0.0.13
Summary: Simple pagination for pydantic models and SQLAlchemy Query objects
Author-email: pablete <jtamayoh@gmail.com>, mike-diomedes <michael.guzman.personal@gmail.com>, jdata <jdmoralesar@gmail.com>
Maintainer-email: pablete <jtamayo@enerbit.co>
License-File: LICENSE.txt
Requires-Python: >=3.7
Requires-Dist: pydantic
Requires-Dist: sqlalchemy
